Metadata-Version: 2.1
Name: xyqsister
Version: 0.0.1
Summary: 写给妹妹的一个小软件（确信）
Home-page: https://github.com/ZHYCarge/sister_xie
Author: ZHYCarge
Author-email: ZHYCarge@126.com
License: UNKNOWN
Platform: UNKNOWN
